logger_patch/__init__.py
logger_patch/logger_patch.py
crewai_logging_patch-0.5.dist-info/LICENSE
crewai_logging_patch-0.5.dist-info/METADATA
crewai_logging_patch-0.5.dist-info/WHEEL
crewai_logging_patch-0.5.dist-info/top_level.txt
crewai_logging_patch-0.5.dist-info/RECORD
