Metadata-Version: 2.1
Name: crewai_logging_patch
Version: 0.5
Home-page: https://github.com/theCyberTech/CrewAI_Logger_Patch
Author: theCyberTech
Author-email: the_t3ch@pm.me
License: MIT
License-File: LICENSE
